PythonShujuKexueBenzhilunChuyi/README.md
PythonShujuKexueBenzhilunChuyi/__init__.py
PythonShujuKexueBenzhilunChuyi/__main__.py
PythonShujuKexueBenzhilunChuyi/file.epub
PythonShujuKexueBenzhilunChuyi/index.html
PythonShujuKexueBenzhilunChuyi/css/__init__.py
PythonShujuKexueBenzhilunChuyi/css/annotations.css
PythonShujuKexueBenzhilunChuyi/css/main.css
PythonShujuKexueBenzhilunChuyi/css/normalize.css
PythonShujuKexueBenzhilunChuyi/css/popup.css
PythonShujuKexueBenzhilunChuyi/font/__init__.py
PythonShujuKexueBenzhilunChuyi/font/fontello.eot
PythonShujuKexueBenzhilunChuyi/font/fontello.svg
PythonShujuKexueBenzhilunChuyi/font/fontello.ttf
PythonShujuKexueBenzhilunChuyi/font/fontello.woff
PythonShujuKexueBenzhilunChuyi/img/__init__.py
PythonShujuKexueBenzhilunChuyi/img/annotator-glyph-sprite.png
PythonShujuKexueBenzhilunChuyi/img/annotator-icon-sprite.png
PythonShujuKexueBenzhilunChuyi/img/apple-touch-icon.png
PythonShujuKexueBenzhilunChuyi/img/cancelfullscreen.png
PythonShujuKexueBenzhilunChuyi/img/close.png
PythonShujuKexueBenzhilunChuyi/img/fullscreen.png
PythonShujuKexueBenzhilunChuyi/img/loader.gif
PythonShujuKexueBenzhilunChuyi/img/menu-icon.png
PythonShujuKexueBenzhilunChuyi/img/save.png
PythonShujuKexueBenzhilunChuyi/img/saved.png
PythonShujuKexueBenzhilunChuyi/img/settings-s.png
PythonShujuKexueBenzhilunChuyi/img/settings.png
PythonShujuKexueBenzhilunChuyi/img/star.png
PythonShujuKexueBenzhilunChuyi/js/__init__.py
PythonShujuKexueBenzhilunChuyi/js/epub.js
PythonShujuKexueBenzhilunChuyi/js/epub.min.js
PythonShujuKexueBenzhilunChuyi/js/epub.min.map
PythonShujuKexueBenzhilunChuyi/js/hooks.min.js
PythonShujuKexueBenzhilunChuyi/js/hooks.min.map
PythonShujuKexueBenzhilunChuyi/js/reader.js
PythonShujuKexueBenzhilunChuyi/js/reader.js.map
PythonShujuKexueBenzhilunChuyi/js/reader.min.js
PythonShujuKexueBenzhilunChuyi/js/reader.min.map
PythonShujuKexueBenzhilunChuyi/js/hooks/__init__.py
PythonShujuKexueBenzhilunChuyi/js/hooks/extensions/__init__.py
python_shuju_kexue_benzhilun_chuyi-2024.3.6.0.dist-info/METADATA
python_shuju_kexue_benzhilun_chuyi-2024.3.6.0.dist-info/WHEEL
python_shuju_kexue_benzhilun_chuyi-2024.3.6.0.dist-info/entry_points.txt
python_shuju_kexue_benzhilun_chuyi-2024.3.6.0.dist-info/top_level.txt
python_shuju_kexue_benzhilun_chuyi-2024.3.6.0.dist-info/RECORD
